{
  "Benefits": [
    {
      "docNo": "MED6100021",
      "claim": "บิดา",
      "name": "นาย  สามารถ   ชยันทำงาน",
      "hospital": "โรงพยาบาลเกษมราษฎร์",
      "hospitalType": "เอกชน",
      "type": "คู่สัญญา",
      "reciveNo": "610001",
      "date": "01/03/2018",
      "amt": "24,500.32",
      "claimAmt": "24,500.32",
      "status": "อนุมัติ",
      "edit" : "0"
    },
    {
      "docNo": "MED6100019",
      "claim": "บิดา",
      "name": "นาย  สามารถ   ชยันทำงาน",
      "hospital": "โรงพยาบาลเกษมราษฎร์",
      "hospitalType": "เอกชน",
      "type": "เบิก",
      "reciveNo": "610001",
      "date": "05/03/2018",
      "amt": "15,000.00",
      "claimAmt": "7,500.00",
      "status": "บันทึก",
      "edit" : "1"
    },
    {
      "docNo": "MED6100016",
      "claim": "บุตร",
      "name": "ด.ช   ใจดี  รักการงาน",
      "hospital": "โรงพยาบาลนพรัตน์",
      "hospitalType": "รัฐบาล",
      "type": "ส่งตัว",
      "reciveNo": "61-3430301",
      "date": "25/02/2018",
      "amt": "38,320.00",
      "claimAmt": "38,320.00",
      "status": "อนุมัติ",
      "edit" : "0"
    }
  ]
}