{
  "Funds": [
    {
      "No": "1",
      "Date": "30/7/2560",
      "Name": "ขอเปลี่ยนโยบาย",
      "OldDesc": "ในช่วงเดือน กันยายน มีผลเดือนพศจิกายน",
      "NewDesc": "ในช่วงเดือน สิงหาคม มีผลเดือนตุลาคม",
      "OldOpenDate": "1/7/2560",
      "NewOpenDate": "1/6/2560",
      "OldCloseDate": "31/8/2560",
      "NewCloseDate": "31/7/2560",
      "OldActionDate": "1/9/2560",
      "NewActionDate": "1/8/2560",
      "UpdateBy": "นาย มั่งมี ศรีสุข"
    },
    {
      "No": "1",
      "Date": "30/7/2560",
      "Name": "ขอเปลี่ยนอัตราสะสม",
      "OldDesc": "ในช่วงเดือน กันยายน มีผลเดือนพศจิกายน",
      "NewDesc": "ในช่วงเดือน สิงหาคม มีผลเดือนตุลาคม",
      "OldOpenDate": "1/7/2560",
      "NewOpenDate": "1/6/2560",
      "OldCloseDate": "31/8/2560",
      "NewCloseDate": "31/7/2560",
      "OldActionDate": "1/9/2560",
      "NewActionDate": "1/8/2560",
      "UpdateBy": "นาย มั่งมี ศรีสุข"
    },
    {
      "No": "1",
      "Date": "30/7/2560",
      "Name": "ขอเปลี่ยนแปลงผู้รับผลประโยชน์",
      "OldDesc": "ในช่วงเดือน กันยายน มีผลเดือนพศจิกายน",
      "NewDesc": "ในช่วงเดือน สิงหาคม มีผลเดือนตุลาคม",
      "OldOpenDate": "1/7/2560",
      "NewOpenDate": "1/6/2560",
      "OldCloseDate": "31/8/2560",
      "NewCloseDate": "31/7/2560",
      "OldActionDate": "1/9/2560",
      "NewActionDate": "1/8/2560",
      "UpdateBy": "นาย มั่งมี ศรีสุข"
    }
  ]
}